solarmax_ardexa.py
solarmax_ardexa-1.0.4.dist-info/DESCRIPTION.rst
solarmax_ardexa-1.0.4.dist-info/METADATA
solarmax_ardexa-1.0.4.dist-info/RECORD
solarmax_ardexa-1.0.4.dist-info/WHEEL
solarmax_ardexa-1.0.4.dist-info/entry_points.txt
solarmax_ardexa-1.0.4.dist-info/metadata.json
solarmax_ardexa-1.0.4.dist-info/top_level.txt
