Metadata-Version: 2.0
Name: solarmax-ardexa
Version: 1.0.4
Summary: Collect from Solarmax Inverters and send the data to your cloud using Ardexa
Home-page: https://github.com/ardexa/solarmax-inverters
Author: Ardexa Pty Limited
Author-email: support@ardexa.com
License: UNKNOWN
Project-URL: Source, https://github.com/ardexa/solarmax-inverters/
Project-URL: Bug Reports, https://github.com/ardexa/solarmax-inverters/issues
Keywords: solarmax solar inverter ardexa
Platform: UNKNOWN
Classifier: License :: OSI Approved :: MIT License
Classifier: Programming Language :: Python :: 2
Classifier: Programming Language :: Python :: 2.7
Classifier: Programming Language :: Python :: 3
Classifier: Programming Language :: Python :: 3.4
Classifier: Programming Language :: Python :: 3.5
Classifier: Programming Language :: Python :: 3.6
Requires-Python: >=2.7
Requires-Dist: Click
Requires-Dist: ardexaplugin
Requires-Dist: future
Requires-Dist: pyserial
